colorize/__init__.py
colorize/colorizer.py
colorize_package-0.3.0.dist-info/LICENSE
colorize_package-0.3.0.dist-info/METADATA
colorize_package-0.3.0.dist-info/WHEEL
colorize_package-0.3.0.dist-info/top_level.txt
colorize_package-0.3.0.dist-info/RECORD
