Metadata-Version: 2.1
Name: colorize-package
Version: 0.3.0
Summary: A simple package to colorize black and white images
Author-email: George Campbell <George@campbellcodes.com>
License: 
Requires-Python: >=3.6
License-File: LICENSE
Requires-Dist: opencv-python >=4.5.3
